CHANGES
COPYING
MANIFEST.in
README
setup.py
authres/__init__.py
authres/__main__.py
authres/arc.py
authres/core.py
authres/dkim_adsp.py
authres/dkim_b.py
authres/dmarc.py
authres/rrvs.py
authres/smime.py
authres/tests
authres/vbr.py
authres.egg-info/PKG-INFO
authres.egg-info/SOURCES.txt
authres.egg-info/dependency_links.txt
authres.egg-info/not-zip-safe
authres.egg-info/top_level.txt